st_copy_button/__init__.py
st_copy_button/example.py
st_copy_button/frontend/.env
st_copy_button/frontend/.prettierrc
st_copy_button/frontend/build/asset-manifest.json
st_copy_button/frontend/build/bootstrap.min.css
st_copy_button/frontend/build/index.html
st_copy_button/frontend/build/static/js/main.b193172b.js
st_copy_button/frontend/build/static/js/main.b193172b.js.map
st_copy_button/frontend/build/style.css
st_copy_button/frontend/package-lock.json
st_copy_button/frontend/package.json
st_copy_button/frontend/public/bootstrap.min.css
st_copy_button/frontend/public/index.html
st_copy_button/frontend/public/style.css
st_copy_button/frontend/src/copyButton.ts
st_copy_button/frontend/src/index.ts
st_copy_button/frontend/src/react-app-env.d.ts
st_copy_button/frontend/src/streamlitApi.ts
st_copy_button/frontend/src/utils.ts
st_copy_button/frontend/tsconfig.json
st_copy_button-0.1.1.dist-info/LICENSE
st_copy_button-0.1.1.dist-info/METADATA
st_copy_button-0.1.1.dist-info/WHEEL
st_copy_button-0.1.1.dist-info/RECORD
