Metadata-Version: 2.1
Name: st-copy-button
Version: 0.1.1
Summary: A simple Streamlit component for copying text to the user's clipboard with one click.
Home-page: https://gitlab.com/james.young2/st-copy-button
License: MIT
Keywords: streamlit,component,clipboard
Author: James Young
Author-email: james.young@ramseysolutions.com
Requires-Python: >=3.9.8,<4.0
Classifier: License :: OSI Approved :: MIT License
Classifier: Programming Language :: Python :: 3
Classifier: Programming Language :: Python :: 3.10
Classifier: Programming Language :: Python :: 3.11
Classifier: Programming Language :: Python :: 3.12
Classifier: Programming Language :: Python :: 3.13
Requires-Dist: streamlit (>=1.31.0,<2.0.0)
Project-URL: Repository, https://gitlab.com/james.young2/st-copy-button
